{"감곡":{"lst":"1850"},"강남대_용인행":{"lst":"2300"},"강릉시외터미널":{"lst":"1840"},"건국대(충주)":{"lst":"0800"},"건국대학교":{"lst":"0800"},"고천":{"lst":"1930"},"고한사북공영":{"lst":"1230"},"공주":{"lst":"0900"},"광교마을앞":{"lst":"2300"},"광주(유·스퀘어)":{"lst":"1600"},"교통대":{"lst":"0800"},"구룡":{"lst":"0700"},"군산":{"lst":"1600"},"기지시":{"lst":"2040"},"기흥역정류소":{"lst":"2300"},"당진":{"lst":"2040"},"대전복합":{"lst":"1940"},"대전청사(선사유적)":{"lst":"1340"},"동백역(참솔마을)":{"lst":"2300"},"마산":{"lst":"2300"},"마천":{"lst":"1520"},"명지대":{"lst":"2300"},"목포":{"lst":"1525"},"무안":{"lst":"1450"},"무안(전남)":{"lst":"1450"},"문막":{"lst":"1930"},"백무동(지리산)":{"lst":"1520"},"보정역":{"lst":"2300"},"서산":{"lst":"2040"},"서상(남덕유산)":{"lst":"1520"},"서수원":{"lst":"0740"},"세종":{"lst":"1340"},"세종청사":{"lst":"1340"},"속초":{"lst":"1730"},"수원광교박물관":{"lst":"2300"},"수원터미널":{"lst":"0740"},"시흥":{"lst":"1500"},"신갈역":{"lst":"2300"},"안동":{"lst":"1500"},"안산터미널":{"lst":"1525"},"안양":{"lst":"1930"},"어송":{"lst":"2040"},"어정역":{"lst":"2300"},"연원마을":{"lst":"2300"},"영광":{"lst":"1450"},"영월":{"lst":"1230"},"영주":{"lst":"1500"},"오산":{"lst":"0740"},"용인":{"lst":"2300"},"용인대":{"lst":"2300"},"운산":{"lst":"2040"},"울산":{"lst":"0740"},"울산신복":{"lst":"0740"},"원주":{"lst":"1930"},"유성복합":{"lst":"1340"},"유성시외":null,"음암":{"lst":"2040"},"익산":{"lst":"1600"},"인월":{"lst":"1520"},"인천공항1터미널":{"lst":"2210"},"전주":{"lst":"1700"},"제천":{"lst":"1850"},"죽전역":{"lst":"2300"},"진도":{"lst":"0800"},"창원":{"lst":"2300"},"천안":{"lst":"1950"},"청주":{"lst":"1840"},"충주":{"lst":"1500"},"태백":{"lst":"1230"},"태안":{"lst":"2040"},"풍기IC":{"lst":"1500"},"풍덕고교사거리":{"lst":"2300"},"함양":{"lst":"1520"},"함평":{"lst":"1450"},"현대홈타운":{"lst":"2300"},"호계동":{"lst":"1930"}}