{"Anpyeong": null, "Baekyangsa": null, "Daeak": null, "Daeheung-ri": null, "Danjeon": null, "Deokjin": null, "Deoksan": null, "Galma": null, "Gangneung Intercity Bus Terminal": null, "Gangseon-dong": null, "Guam": null, "Gusan": null, "Gwangju (U Square)": null, "Gweoljeon": null, "Haman, Yongdu": null, "Hwangryongyo": null, "Jangsan": null, "Jangseong": null, "Jangseong Dam (waterside road)": null, "Jangseong-eup": null, "Jeongeup": null, "Myeongchi": null, "Punggi": null, "Seongam": null, "Seongsan-ri": null, "Sinchon": null, "Sinheung": null, "Sokcho": null, "Udong (Yonggang)": null, "Uji": null, "Unamdong": null, "Wolseong Entrance": null, "Yaeun-ri": null, "Yaksu-ri": null, "Yongam": null}