{"Andong":{"lst":"1830"},"Ansan Terminal":{"lst":"2359"},"Bug-gu":{"lst":"0934"},"Changwon":{"lst":"2110"},"Changwon Namsan":{"lst":"2110"},"Chuncheon":{"lst":"1810"},"Chungju":{"lst":"1900"},"Dong-hae":{"lst":"2330"},"Eonyang":{"lst":"2130"},"Gangneung Intercity Bus Terminal":{"lst":"2330"},"Ganseong":{"lst":"1412"},"Geoje (Gohyeon)":{"lst":"2100"},"Geojin":{"lst":"1412"},"Gohansa Buk Gongyeong":{"lst":"1531"},"Gumi":{"lst":"1935"},"Gunsan":{"lst":"1900"},"Gyeongju Intercity Bus Terminal":{"lst":"2200"},"Hongcheon":{"lst":"1810"},"Hosan":{"lst":"1531"},"Icheon":{"lst":"1840"},"Iksan":{"lst":"1900"},"Incheon Airport Terminal 1":{"lst":"2345"},"Incheon Airport Terminal 2":{"lst":"2345"},"Jecheon":{"lst":"1830"},"Jeomchon":{"lst":"1935"},"Jinhae":{"lst":"1810"},"Jinju":{"lst":"2040"},"Kkotdongsan":{"lst":"1830"},"Masan":{"lst":"2320"},"Masan South":{"lst":"2110"},"Ongcheon":{"lst":"1830"},"Osan":{"lst":"2359"},"Pohang":{"lst":"2200"},"Samcheok":{"lst":"1608"},"Sangju City Outskirts":{"lst":"1935"},"Sangju Integrated Bus Terminal":{"lst":"1935"},"Seokgye":{"lst":"2130"},"Sokcho":{"lst":"2330"},"Suwon Terminal":{"lst":"2359"},"Tae-baek":{"lst":"1531"},"Tongdosa Temple (Sinpyeong)":{"lst":"2130"},"Tongyeong":{"lst":"2100"},"Uljin":{"lst":"1531"},"Wonju":{"lst":"1810"},"Yeoju":{"lst":"1840"},"Yeongcheon":{"lst":"1800"},"Yeongju":{"lst":"1830"}}