{"갈사":null,"계항":null,"계황":null,"고내":null,"고전":null,"고전상성":null,"고전지소":null,"고전합진":null,"고포":null,"곤양":null,"광양":null,"광포":null,"구례":null,"구정":null,"구학":null,"궁항":null,"기본요금":null,"남양":null,"남해":null,"대덕":null,"대사":null,"대송":null,"대전복합":null,"덕오":null,"덕천":null,"덕천(농촌)":null,"도마":null,"동광양(중마)":null,"동산":null,"마산":null,"마치":null,"명덕":null,"문의":null,"문항":null,"미법":null,"미조":null,"박달":null,"부산서부(사상)":null,"사등":null,"상신월":null,"상주":null,"서근":null,"서울남부":null,"석교":null,"설천":null,"섬진강문화센타":null,"세곡":null,"소송":null,"송정":null,"순천":null,"신노량":null,"신도":null,"신방촌":null,"신전":null,"쌍계사":null,"양보":null,"왕지":null,"우복":null,"원곡":null,"월운":null,"이동":null,"장암":null,"장암상쌍":null,"적량":null,"전도":null,"전도(농촌)":null,"전도(완)":null,"조금":null,"주유소":null,"진목":null,"진정":null,"진주":null,"차면":null,"창원":null,"통정":null,"하동":null,"하동(완)":null,"하신월":null,"하장암":null,"합진":null,"화계":null,"화엄사":null,"황토길":null,"횡천":null,"횡천(남산)":null,"횡천대덕":null,"횡천여의":null}