{"Anmyeondo":{"lst":"1900"},"Asan Onyang":null,"Bonggang Bridge":{"lst":"1330"},"Central City (Seoul)":{"lst":"1730"},"Changgi-ri":{"lst":"1900"},"Cheonan":{"lst":"1330"},"Cheonan Asan Station":{"lst":"1330"},"Daejeon Complex":{"lst":"1725"},"Dangjin":{"lst":"0715"},"Eosong":{"lst":"1725"},"Eumam":{"lst":"0715"},"Gijisi":{"lst":"0715"},"Guryong (Buyeo)":{"lst":"0715"},"Haemi":{"lst":"1900"},"Hanseo University":{"lst":"1900"},"Sapgyocheon":{"lst":"0715"},"Seosan":{"lst":"1900"},"Seoul Southern":{"lst":"1900"},"Sinpyeong":{"lst":"0715"},"Ssangyong-dong":{"lst":"1330"},"Tae-an":{"lst":"1725"},"Tae-an-nam-myeon":{"lst":"1725"},"Unsan":{"lst":"0715"}}