{"data":[{"cd":"2238201","nm":"인천공항1터미널"},{"cd":"2238202","nm":"인천공항2터미널"},{"cd":"2482701","nm":"속초"},{"cd":"2551901","nm":"강릉시외터미널"},{"cd":"2600701","nm":"태백"},{"cd":"2623601","nm":"영월"},{"cd":"2636801","nm":"문막"},{"cd":"2638201","nm":"원주"},{"cd":"2716501","nm":"제천"},{"cd":"2736001","nm":"충주"},{"cd":"2747801","nm":"건국대(충주)"},{"cd":"2761001","nm":"감곡"},{"cd":"2839701","nm":"청주"},{"cd":"3010701","nm":"세종청사"},{"cd":"3015401","nm":"세종"},{"cd":"3112001","nm":"천안"},{"cd":"3173301","nm":"기지시"},{"cd":"3177101","nm":"당진"},{"cd":"3192401","nm":"어송"},{"cd":"3193601","nm":"음암"},{"cd":"3194501","nm":"운산"},{"cd":"3198101","nm":"서산"},{"cd":"3214401","nm":"태안"},{"cd":"3258501","nm":"공주"},{"cd":"3417501","nm":"유성시외"},{"cd":"3455101","nm":"대전복합"},{"cd":"3520501","nm":"대전청사(선사유적)"},{"cd":"3604501","nm":"풍기IC"},{"cd":"3607801","nm":"영주"},{"cd":"3663601","nm":"안동"},{"cd":"4472001","nm":"울산"},{"cd":"5000101","nm":"서상(남덕유산)"},{"cd":"5003901","nm":"함양"},{"cd":"5005501","nm":"마천"},{"cd":"5005701","nm":"지리산(백무동)"},{"cd":"5135601","nm":"마산"},{"cd":"5139301","nm":"창원"},{"cd":"5493301","nm":"전주시외터미널"},{"cd":"5571501","nm":"인월"},{"cd":"5704301","nm":"영광"},{"cd":"5715301","nm":"함평"},{"cd":"5852401","nm":"무안(전남)"},{"cd":"5864201","nm":"목포"},{"cd":"5892201","nm":"진도"},{"cd":"6193701","nm":"광주(유·스퀘어)"}]}