{"강진":{"lst":"1850"},"강진(전남)":{"lst":"1850"},"고흥":{"lst":"1920"},"과역":{"lst":"1920"},"광영":{"lst":"0920"},"광주(유·스퀘어)":{"lst":"2000"},"금호리":{"lst":null},"김해":{"lst":"1350"},"남악":{"lst":"2055"},"남창":{"lst":"1850"},"녹동":{"lst":"1920"},"대구서부":{"lst":"1830"},"대전복합":{"lst":"1130"},"대전청사(선사유적)":{"lst":"1130"},"도촌":{"lst":null},"독천":{"lst":"1230"},"동광양(중마)":{"lst":"2020"},"동대구":{"lst":"1030"},"동서울":{"lst":"0820"},"목포":{"lst":"2055"},"문화동":{"lst":"0620"},"배산":{"lst":"1850"},"벌교":{"lst":"1920"},"보성":{"lst":"1850"},"부산":{"lst":"1950"},"부산서부(사상)":{"lst":"2020"},"삼호":{"lst":"2055"},"성남":{"lst":"0920"},"성전":{"lst":"1230"},"성황":{"lst":null},"센트럴시티(서울)":{"lst":"1940"},"수원터미널":{"lst":"0920"},"순천":{"lst":"2150"},"안산터미널":{"lst":"0830"},"여수":{"lst":"1240"},"여수(대교)":{"lst":"1940"},"여천":{"lst":"1240"},"예당":{"lst":"1850"},"완도":{"lst":"1850"},"울산":{"lst":"1350"},"원동":{"lst":"1850"},"월송":{"lst":"1850"},"인천":{"lst":"0830"},"인천공항1터미널":{"lst":"0215"},"인천공항2터미널":{"lst":"0215"},"장흥":{"lst":"1850"},"정안(휴)상행":{"lst":"1750"},"조성":{"lst":"1850"},"진교":{"lst":"2005"},"진도":{"lst":"1620"},"진주":{"lst":"2005"},"태인교":{"lst":"2035"},"해남":{"lst":"1850"}}