{"Cheongju Express Bus Terminal": {"last_start_date": "1930"}, "Daegu Yonggye": {"last_start_date": "2200"}, "Dangjin": null, "Dangjin Gijisi": null, "Dongdaegu": {"last_start_date": "2200"}, "Dongseoul": {"last_start_date": "1730"}, "Guri": null, "Gwangju (U Square)": {"last_start_date": "2230"}, "Incheon": {"last_start_date": "2200"}, "Jeonju Express Bus Terminal": {"last_start_date": "2220"}, "Nakdong River (Holiday) Upbound": {"last_start_date": "1900"}, "Nonsan": {"last_start_date": "1500"}, "Seomjingang (rest)upbound": {"last_start_date": "1710"}, "Seongnam (Bundang)": {"last_start_date": "1840"}, "Seoul Gyeongbu": {"last_start_date": "2350"}, "Suncheon": {"last_start_date": "1830"}, "Uijeongbu": null, "Yeocheon": {"last_start_date": "1830"}, "Yeonmudae": {"last_start_date": "1500"}, "Yeosu": {"last_start_date": "1830"}, "Yongin": {"last_start_date": "1900"}, "Yongin Singal (under the overpass)": {"last_start_date": "1900"}}