{"갈산":{"lst":"0820"},"고북":{"lst":"0820"},"구항":{"lst":"0820"},"기지시":{"lst":"1620"},"남면(태안)":{"lst":"0820"},"당진":{"lst":"1620"},"대전복합":{"lst":"1735"},"동성":{"lst":"0820"},"봉강교":{"lst":"1740"},"서산":{"lst":"1620"},"서울남부":{"lst":"0725"},"성남":{"lst":"1620"},"센트럴시티(서울)":{"lst":"1730"},"신례원":{"lst":"0820"},"아산(온양)":{"lst":"1740"},"어송":{"lst":"0820"},"예산":{"lst":"0820"},"운산":{"lst":"1620"},"음암":{"lst":"1620"},"창기리":{"lst":"1730"},"천안":{"lst":"1740"},"천안아산(KTX)역":{"lst":"1740"},"천안아산역":{"lst":"1740"},"태안":{"lst":"1620"},"태안남면":{"lst":"1620"},"해미":{"lst":"0820"}}