{"강릉시외터미널":{"lst":"2310"},"진주경상대(칠암)":{"lst":"2035"},"상주종합버스터미널":{"lst":"1923"},"속초시외":{"lst":"2300"},"통영종합터미널":{"lst":"2020"},"간성":{"lst":"1130"},"거진":{"lst":"1120"},"동해":{"lst":"2350"},"포항":{"lst":"2200"},"홍천":{"lst":"1850"},"경주시외":{"lst":"2240"},"수원터미널":{"lst":"1850"},"낙산":{"lst":"2315"},"마산":{"lst":"2320"},"양양":{"lst":"2320"},"여주":{"lst":"1915"},"오산":{"lst":"1910"},"울진":{"lst":"1825"},"원주":{"lst":"1950"},"이천":{"lst":"1840"},"춘천":{"lst":"1810"},"충주":{"lst":"1850"},"거제(고현)":{"lst":"2100"},"구미":{"lst":"2015"},"마산남부":{"lst":"2100"},"부산동래":{"lst":"2040"},"진주":{"lst":"2030"},"진해":{"lst":"1320"},"안동":{"lst":"1840"},"영주":{"lst":"1730"},"예천":{"lst":"1800"},"진주(개양)":{"lst":"2043"},"군산":{"lst":"1830"},"언양":{"lst":"2130"},"익산":{"lst":"1910"},"점촌":{"lst":"1900"},"고한사북공영":{"lst":"1640"},"태백":{"lst":"1705"},"제천":{"lst":"0840"},"영천":{"lst":"1800"},"예천삼거리":{"lst":"1802"},"옹천":{"lst":"1820"},"물치":{"lst":"2310"},"호산":{"lst":"1535"},"안산":{"lst":"2340"},"인천공항T1":{"lst":"2350"},"인천공항T2":{"lst":"2330"},"경북도청(신도청)":{"lst":"1818"}}