{"data":[{"cd":"2638201","nm":"원주"},{"cd":"3607801","nm":"영주"},{"cd":"3663601","nm":"안동"},{"cd":"3675601","nm":"일직"},{"cd":"3732801","nm":"단촌"},{"cd":"3733501","nm":"의성"},{"cd":"3736202","nm":"도리원"},{"cd":"3776001","nm":"포항"},{"cd":"3815701","nm":"경주시외"},{"cd":"3843601","nm":"하양"},{"cd":"3845402","nm":"대구대"},{"cd":"3888501","nm":"영천"},{"cd":"3901801","nm":"군위"},{"cd":"3902801","nm":"효령"},{"cd":"4105201","nm":"대구공항"},{"cd":"4124601","nm":"동대구"},{"cd":"4248201","nm":"대구서부"},{"cd":"4472001","nm":"울산"},{"cd":"4809501","nm":"부산해운대"},{"cd":"5135601","nm":"마산"},{"cd":"5139301","nm":"창원"},{"cd":"6193701","nm":"광주(유·스퀘어)"}]}