{"거제(고현)": {"last_start_date": "1255"}, "경북도청(신도청)": {"last_start_date": "1820"}, "경주시외터미널": {"last_start_date": "1520"}, "계룡": {"last_start_date": "2031"}, "계룡(공주)": null, "공주": {"last_start_date": "2220"}, "공주대": {"last_start_date": "2220"}, "광주(유·스퀘어)": {"last_start_date": "1900"}, "구룡": {"last_start_date": "2020"}, "구룡(당)": null, "군산": {"last_start_date": "1550"}, "기지시": {"last_start_date": "2020"}, "기흥역정류소": {"last_start_date": "2050"}, "내포": {"last_start_date": "0849"}, "노성": {"last_start_date": "2031"}, "논산": {"last_start_date": "2031"}, "당진": {"last_start_date": "2020"}, "대전복합": {"last_start_date": "1905"}, "대전서부": {"last_start_date": "1600"}, "대전청사(선사유적)": {"last_start_date": "1532"}, "덕산": {"last_start_date": "0849"}, "동서울": {"last_start_date": "1930"}, "동탄역": {"last_start_date": "2050"}, "봉황(공주)": null, "봉황(공주시)": {"last_start_date": "1730"}, "부여": {"last_start_date": "1920"}, "부천": {"last_start_date": "1835"}, "사곡": {"last_start_date": "0849"}, "삽교": {"last_start_date": "0849"}, "상월": {"last_start_date": "2031"}, "서산": {"last_start_date": "2020"}, "서울남부": {"last_start_date": "2040"}, "서천": {"last_start_date": "1550"}, "성남": {"last_start_date": "1845"}, "세종청사": {"last_start_date": "2055"}, "수원터미널": {"last_start_date": "1840"}, "신갈(용인)": {"last_start_date": "2050"}, "신양": {"last_start_date": "0849"}, "신평": {"last_start_date": "2020"}, "신풍": {"last_start_date": "0849"}, "안동": {"last_start_date": "1820"}, "안양": {"last_start_date": "1915"}, "어송": {"last_start_date": "2020"}, "예산": {"last_start_date": "0849"}, "오산": {"last_start_date": "1840"}, "용인": {"last_start_date": "2050"}, "우성": {"last_start_date": "0849"}, "운산": {"last_start_date": "2020"}, "유구": {"last_start_date": "0849"}, "유성시외": {"last_start_date": "1850"}, "음암": {"last_start_date": "2020"}, "이인": {"last_start_date": "1730"}, "인천": {"last_start_date": "1920"}, "인천공항1터미널": {"last_start_date": "1630"}, "인천공항2터미널": {"last_start_date": "1630"}, "임성동": {"last_start_date": "0849"}, "자운대": {"last_start_date": "2035"}, "장기": {"last_start_date": "2220"}, "전주": {"last_start_date": "1312"}, "조치원": {"last_start_date": "2055"}, "천안": {"last_start_date": "2005"}, "청주": {"last_start_date": "2055"}, "춘천": {"last_start_date": "1640"}, "탄천": {"last_start_date": "1730"}, "태안": {"last_start_date": "2020"}, "평촌": {"last_start_date": "0935"}, "포항": {"last_start_date": "1520"}, "하마루": {"last_start_date": "2031"}, "한서대": {"last_start_date": "0849"}, "합덕": {"last_start_date": "2020"}, "해미": {"last_start_date": "0849"}, "홍성": {"last_start_date": "0715"}}