{"고흥": {"last_start_date": "1955"}, "곡천": {"last_start_date": "2104"}, "과역": {"last_start_date": "1955"}, "광양": {"last_start_date": "1815"}, "광주(유·스퀘어)": {"last_start_date": "2104"}, "녹동": {"last_start_date": "1955"}, "동광양(중마)": {"last_start_date": "1815"}, "부산서부": {"last_start_date": "1815"}, "부산서부(사상)": null, "섬진강(상행)": {"last_start_date": "0945"}, "섬진강환승(상행)": {"last_start_date": "0945"}, "섬진강환승(하행)": {"last_start_date": "1155"}, "센트럴시티(서울)": {"last_start_date": "1540"}, "소태": {"last_start_date": "1043"}, "소태역": {"last_start_date": "2104"}, "순천": {"last_start_date": "1815"}, "학동": {"last_start_date": "2104"}, "화순": {"last_start_date": "2104"}}