{"가락시장":{"lst":"2115"},"가천대학교":{"lst":"2115"},"갈산":{"lst":"2025"},"강남대":{"lst":"2000"},"경기-중앙대":{"lst":"1020"},"고북":{"lst":"2025"},"공도":{"lst":"1020"},"공주":{"lst":"1210"},"구룡":{"lst":"1930"},"기지시":{"lst":"2145"},"대림동산":{"lst":"1020"},"대전":{"lst":"2045"},"동서울":{"lst":"2115"},"명지대":{"lst":"2000"},"무주안성":{"lst":"1020"},"배방정류소":{"lst":"2100"},"봉황(공주시)":{"lst":"1210"},"삽교천":{"lst":"2045"},"서부휴게소(아산)":{"lst":"2200"},"서울-장지역":{"lst":"2115"},"성남":{"lst":"1605"},"세종그랑시아":{"lst":"2000"},"신갈(용인)":{"lst":"2000"},"신례원":{"lst":"2145"},"신창":{"lst":"2145"},"안면도":{"lst":"1940"},"용인":{"lst":"2000"},"인천공항1터미널":{"lst":"1930"},"인천공항2터미널":{"lst":"1930"},"임성동":{"lst":"2025"},"잠실역":{"lst":"2115"},"창기리":{"lst":"1940"},"천안고속":{"lst":"2200"},"청주공항":{"lst":"1630"},"청주북부터미널":{"lst":"1630"},"충남-구항":{"lst":"2025"},"충남-내포":{"lst":"2025"},"충남-당진":{"lst":"2145"},"충남-동성":{"lst":"2025"},"충남-만리포":{"lst":"1840"},"충남-방앗간":{"lst":"2135"},"충남-소원":{"lst":"1840"},"충남-어송":{"lst":"2135"},"충남-태안":{"lst":"2135"},"충남-한서대":{"lst":"1905"},"충북-청주":{"lst":"2100"},"태안남면":{"lst":"1940"},"합덕":{"lst":"2145"},"행정타운,용인대":{"lst":"2000"},"홍성":{"lst":"2025"}}