{"갈산": {"last_start_date": "2105"}, "고북": {"last_start_date": "2105"}, "공도": {"last_start_date": "1210"}, "공암": {"last_start_date": "0904"}, "공주": {"last_start_date": "1012"}, "구항": {"last_start_date": "2105"}, "내포": {"last_start_date": "2105"}, "대전복합": {"last_start_date": "1815"}, "대전서남부": {"last_start_date": "0904"}, "대전청사(선사유적)": {"last_start_date": "1815"}, "덕산": null, "덕산스파": {"last_start_date": "2030"}, "동성": {"last_start_date": "2105"}, "보령(대천)": {"last_start_date": "0835"}, "사곡": {"last_start_date": "0904"}, "삽교": null, "서산": {"last_start_date": "2105"}, "센트럴시티(서울)": {"last_start_date": "2030"}, "신례원": null, "신창": {"last_start_date": "2050"}, "신풍": {"last_start_date": "0904"}, "안성": {"last_start_date": "1210"}, "어송": {"last_start_date": "2105"}, "우성": {"last_start_date": "0904"}, "운곡": {"last_start_date": "0835"}, "유구": {"last_start_date": "0904"}, "유성시외": {"last_start_date": "1012"}, "인천": {"last_start_date": "1905"}, "중앙대(안성)": {"last_start_date": "1210"}, "청양": {"last_start_date": "0835"}, "태안": {"last_start_date": "2105"}, "한서대": null, "해미": null, "홍성": {"last_start_date": "2105"}}