{"Bisan": {"lst": "0700"}, "Bocheon": {"lst": "0700"}, "Cheongju": {"lst": "0700"}, "Cheongju University Bus Stop": {"lst": "0700"}, "Chungju": {"lst": "1620"}, "Danseong": {"lst": "1620"}, "Deoksan (Jecheon)": {"lst": "1620"}, "Doan": {"lst": "0700"}, "Dongseoul": {"lst": "1730"}, "Eumseong": {"lst": "0700"}, "Gagok": {"lst": "1900"}, "Guinsa": {"lst": "1900"}, "Gyeran-ri": {"lst": "1620"}, "Janghoe": {"lst": "1620"}, "Jeokgok-ri": {"lst": "1620"}, "Jeungpyeong": {"lst": "0700"}, "Ju Deok": {"lst": "0700"}, "Salmi": {"lst": "1620"}, "Susan": {"lst": "1620"}, "Susan Lee": {"lst": "1620"}, "Tanjiri": {"lst": "1620"}, "Yeongchun": {"lst": "1900"}, "Yongbawi": {"lst": "1620"}}