{"data":[{"cd":"2015","nm":"삼척"},{"cd":"2039","nm":"태백"},{"cd":"2051","nm":"강릉시외터미널"},{"cd":"2087","nm":"마차역"},{"cd":"2088","nm":"하장입구"},{"cd":"2089","nm":"도경"},{"cd":"2575","nm":"통리"},{"cd":"2576","nm":"미로"},{"cd":"2671","nm":"동해"},{"cd":"2727","nm":"상거노"},{"cd":"2728","nm":"하정"},{"cd":"2729","nm":"상정"},{"cd":"2730","nm":"천기"},{"cd":"2731","nm":"신기"},{"cd":"2732","nm":"안의리"},{"cd":"2733","nm":"감나무골"},{"cd":"2734","nm":"발리"},{"cd":"2735","nm":"하고사리"},{"cd":"2736","nm":"늑구"},{"cd":"2737","nm":"마교"},{"cd":"2738","nm":"흥전"},{"cd":"2739","nm":"나한정"},{"cd":"2740","nm":"심포"},{"cd":"2796","nm":"도계시내"},{"cd":"2916","nm":"삼척(시내좌석)"}]}