{"data":[{"cd":"6001","nm":"거창"},{"cd":"6032","nm":"함양"},{"cd":"7010","nm":"남원"},{"cd":"7015","nm":"무주"},{"cd":"7020","nm":"순창"},{"cd":"7022","nm":"안성(전북)"},{"cd":"7027","nm":"인월(지리산둘레길)"},{"cd":"7029","nm":"장계"},{"cd":"7030","nm":"장수"},{"cd":"7031","nm":"적상"},{"cd":"7046","nm":"금성"},{"cd":"7057","nm":"강천사"},{"cd":"7061","nm":"계북"},{"cd":"7070","nm":"적성"},{"cd":"7072","nm":"금과"},{"cd":"7082","nm":"번암"},{"cd":"7104","nm":"계남"},{"cd":"8003","nm":"곡성"},{"cd":"8007","nm":"구례"},{"cd":"8014","nm":"담양"},{"cd":"8038","nm":"순천"},{"cd":"8041","nm":"여수"},{"cd":"8042","nm":"여천"},{"cd":"8048","nm":"옥과"},{"cd":"8068","nm":"석곡"},{"cd":"8069","nm":"순천북부"},{"cd":"8113","nm":"덕양"},{"cd":"8138","nm":"화엄사"},{"cd":"8430","nm":"죽곡"},{"cd":"8488","nm":"광천(전남)"},{"cd":"9204","nm":"대구서부"}]}