{"거제(고현)":null,"거제옥포":null,"경주":null,"경주시외터미널":null,"고성":null,"광주(유·스퀘어)":null,"김해":null,"김해공항":null,"대구서부":null,"대전복합":null,"동서울":null,"마산남부":null,"무전동":null,"배둔":null,"부산동래":null,"부산동부":null,"부산서부(사상)":null,"부산해운대":null,"부포":null,"사곡":null,"사천":null,"사천공항":null,"상리":null,"서울경부":null,"서울남부":null,"성남":null,"수원터미널":null,"안산터미널":null,"오산":null,"용원사거리":null,"울산":null,"인삼랜드(휴)상행":null,"인천":null,"인천공항1터미널":null,"인천공항2터미널":null,"장승포시외":null,"장유":null,"진동":null,"진주":null,"창원":null,"창원남산":null,"청주":null,"포항":null}