{"data":[{"cd":"0511601","nm":"동서울"},{"cd":"1349701","nm":"성남"},{"cd":"1454501","nm":"부천"},{"cd":"1658501","nm":"수원터미널"},{"cd":"1671301","nm":"영통입구"},{"cd":"1706301","nm":"용인"},{"cd":"1706502","nm":"기흥역"},{"cd":"1709401","nm":"신갈(용인)"},{"cd":"2224201","nm":"인천"},{"cd":"2238201","nm":"인천공항1터미널"},{"cd":"2238202","nm":"인천공항2터미널"},{"cd":"2460501","nm":"백담사"},{"cd":"2461201","nm":"원통"},{"cd":"2463501","nm":"인제"},{"cd":"2464801","nm":"신남"},{"cd":"2482701","nm":"속초"},{"cd":"2513501","nm":"홍천"},{"cd":"2523401","nm":"횡성"},{"cd":"2551901","nm":"강릉시외터미널"},{"cd":"2638201","nm":"원주"},{"cd":"2736001","nm":"충주"},{"cd":"2773901","nm":"충북혁신도시"},{"cd":"2783101","nm":"진천"},{"cd":"2812001","nm":"청주북부터미널"},{"cd":"2814201","nm":"청주공항"},{"cd":"2839701","nm":"청주"},{"cd":"2863501","nm":"남청주"},{"cd":"3010701","nm":"세종청사"},{"cd":"3015401","nm":"세종"},{"cd":"3112001","nm":"천안"},{"cd":"3148401","nm":"배방정류소"},{"cd":"3149301","nm":"서부휴게소(아산)"},{"cd":"3151704","nm":"아산(온양)"},{"cd":"3173301","nm":"기지시"},{"cd":"3174801","nm":"신평"},{"cd":"3177101","nm":"당진"},{"cd":"3178902","nm":"구룡(당)"},{"cd":"3181201","nm":"합덕"},{"cd":"3193601","nm":"음암"},{"cd":"3194501","nm":"운산"},{"cd":"3196001","nm":"해미"},{"cd":"3196201","nm":"한서대"},{"cd":"3198101","nm":"서산"},{"cd":"3214401","nm":"태안"},{"cd":"3222001","nm":"홍성"},{"cd":"3228301","nm":"금당"},{"cd":"3229901","nm":"천태"},{"cd":"3240801","nm":"덕산(충남)"},{"cd":"3241101","nm":"삽교"},{"cd":"3241601","nm":"내포"},{"cd":"3242101","nm":"신례원"},{"cd":"3242801","nm":"예산"},{"cd":"3243801","nm":"임성동"},{"cd":"3245301","nm":"신양"},{"cd":"3250601","nm":"유구"},{"cd":"3252001","nm":"사곡"},{"cd":"3252501","nm":"신풍"},{"cd":"3253001","nm":"우성"},{"cd":"3253801","nm":"공주(산성)"},{"cd":"3258501","nm":"공주"},{"cd":"3262201","nm":"공암"},{"cd":"3295401","nm":"논산"},{"cd":"3299201","nm":"건양대"},{"cd":"3300801","nm":"연무대"},{"cd":"3301101","nm":"논산TG"},{"cd":"3302001","nm":"은진"},{"cd":"3315201","nm":"부여"},{"cd":"3320001","nm":"홍산"},{"cd":"3331601","nm":"비봉"},{"cd":"3332601","nm":"청양"},{"cd":"3334501","nm":"주정"},{"cd":"3334601","nm":"정산"},{"cd":"3334602","nm":"마티"},{"cd":"3335701","nm":"안심"},{"cd":"3335901","nm":"목면"},{"cd":"3345801","nm":"보령(대천)"},{"cd":"5403701","nm":"군산"},{"cd":"5406001","nm":"대야"},{"cd":"5467401","nm":"익산"},{"cd":"5490001","nm":"덕진동"},{"cd":"5493301","nm":"전주시외터미널"}]}