{"강진(전남)": {"last_start_date": "2210"}, "광주(유·스퀘어)": {"last_start_date": "2050"}, "나주": {"last_start_date": "2050"}, "나주혁신도시": {"last_start_date": "2000"}, "남리": {"last_start_date": "1645"}, "남악": {"last_start_date": "1500"}, "남창": {"last_start_date": "1945"}, "녹진": {"last_start_date": "1645"}, "독천": {"last_start_date": "1500"}, "땅끝": {"last_start_date": "1030"}, "목포": {"last_start_date": "1500"}, "배산": {"last_start_date": "2100"}, "벌교": {"last_start_date": "1830"}, "보성": {"last_start_date": "2100"}, "부산서부": null, "삼호": {"last_start_date": "1500"}, "송정역": {"last_start_date": "2000"}, "순천": {"last_start_date": "1830"}, "신북(전남)": {"last_start_date": "2050"}, "여수": {"last_start_date": "1830"}, "영산포": {"last_start_date": "2050"}, "영암": {"last_start_date": "2050"}, "옥동(전남)": {"last_start_date": "1645"}, "완도": {"last_start_date": "1945"}, "우수영": {"last_start_date": "1645"}, "원동": {"last_start_date": "1945"}, "월송": {"last_start_date": "1945"}, "장흥": {"last_start_date": "2100"}, "진도": {"last_start_date": "1645"}, "진월동": {"last_start_date": "2050"}, "해남": {"last_start_date": "2150"}}